zzlovecccclovezz/__init__.py
zzlovecccclovezz/zz.py
zzlovecccclovezz-1.0.dist-info/licenses/LICENSE
zzlovecccclovezz-1.0.dist-info/METADATA
zzlovecccclovezz-1.0.dist-info/WHEEL
zzlovecccclovezz-1.0.dist-info/top_level.txt
zzlovecccclovezz-1.0.dist-info/RECORD
